RawHandler/RawDataset.py
RawHandler/RawHandler.py
RawHandler/__init__.py
RawHandler/utils.py
rawhandler-0.0.3.dist-info/licenses/LICENSE
rawhandler-0.0.3.dist-info/METADATA
rawhandler-0.0.3.dist-info/WHEEL
rawhandler-0.0.3.dist-info/top_level.txt
rawhandler-0.0.3.dist-info/RECORD
