Metadata-Version: 2.4
Name: RawHandler
Version: 0.0.3
Summary: A basic library to handle camera raw files for use in machine learning. Built on rawpy and cv2.
Author: Ryan Mueller
License: MIT License
Project-URL: Homepage, https://github.com/rymuelle/RawHandler
Project-URL: Bug Tracker, https://github.com/rymuelle/RawHandler/issues
Keywords: python,Machine Learning,Camera Raw
Classifier: Programming Language :: Python :: 3
Classifier: License :: OSI Approved :: MIT License
Classifier: Operating System :: OS Independent
Requires-Python: >=3.8
License-File: LICENSE
Requires-Dist: numpy>=1.24.0
Requires-Dist: rawpy>=0.24.0
Requires-Dist: colour_demosaicing>=0.2.6
Requires-Dist: exifread>=3.3.1
Provides-Extra: torch
Requires-Dist: torch>=2.7.0; extra == "torch"
Provides-Extra: example
Requires-Dist: requests>=2.32.3; extra == "example"
Dynamic: license-file
